.coveragerc
CHANGES.md
LICENSE.txt
MANIFEST.in
README.md
setup.cfg
setup.py
keyrings/__init__.py
keyrings.cryptfile.egg-info/PKG-INFO
keyrings.cryptfile.egg-info/SOURCES.txt
keyrings.cryptfile.egg-info/dependency_links.txt
keyrings.cryptfile.egg-info/entry_points.txt
keyrings.cryptfile.egg-info/requires.txt
keyrings.cryptfile.egg-info/top_level.txt
keyrings/cryptfile/__init__.py
keyrings/cryptfile/convert.py
keyrings/cryptfile/cryptfile.py
keyrings/cryptfile/escape.py
keyrings/cryptfile/file.py
keyrings/cryptfile/file_base.py
tests/__init__.py
tests/requirements.txt
tests/test_cryptfile.py
tests/test_file.py