Metadata-Version: 2.1
Name: keyrings.cryptfile
Version: 1.3.6
Summary: Encrypted file keyring backend
Home-page: https://github.com/frispete/keyrings.cryptfile
Author: Hans-Peter Jansen
Author-email: hpj@urpla.net
License: MIT
Platform: UNKNOWN
Classifier: Development Status :: 5 - Production/Stable
Classifier: Intended Audience :: Developers
Classifier: License :: OSI Approved :: MIT License
Classifier: Programming Language :: Python :: 3.5
Classifier: Programming Language :: Python :: 3.6
Classifier: Programming Language :: Python :: 3.7
Requires-Python: >=3.5
